shared/__init__.py
shared/constants.py
shared/error_handlers.py
shared/exceptions.py
shared/http_client.py
shared/logger.py
shared/response.py
shared/config/__init__.py
shared/config/rabbitmq_config.py
shared/config/settings.py
shared/decorators/__init__.py
shared/decorators/auth_required.py
shared/decorators/validate_input.py
shared/middleware/__init__.py
shared/middleware/auth_middleware.py
shared/middleware/request_logger.py
shared/schemas/__init__.py
shared/utils/__init__.py
shared/utils/datetime.py
shared/utils/jwt_helper.py
shared/utils/password.py
shared/utils/rabbitmq_helper.py
shared/utils/rpc_manager.py
shared/utils/uuid_helper.py
crawl_data_shared-0.1.2.dist-info/METADATA
crawl_data_shared-0.1.2.dist-info/WHEEL
crawl_data_shared-0.1.2.dist-info/top_level.txt
crawl_data_shared-0.1.2.dist-info/RECORD
